<?xml version="1.0" encoding="UTF-8"?>
<metadata xml:lang="en"><Esri><CreaDate>20191204</CreaDate><CreaTime>22032600</CreaTime><ArcGISstyle>FGDC CSDGM Metadata</ArcGISstyle><SyncOnce>FALSE</SyncOnce><DataProperties><itemProps><imsContentType export="True">002</imsContentType><itemLocation><linkage Sync="TRUE">file://\\eco.neoninternal.org\neon\Science\GISData\TOS\TOS_Plot_Data\roads\14_R_JORN_Updated_Roads</linkage><protocol Sync="TRUE">Local Area Network</protocol></itemLocation><itemName Sync="TRUE">Roads_12Jun13</itemName><nativeExtBox><westBL Sync="TRUE">289691.142500</westBL><eastBL Sync="TRUE">378805.512100</eastBL><southBL Sync="TRUE">3564458.146100</southBL><northBL Sync="TRUE">3653203.088500</northBL><exTypeCode Sync="TRUE">1</exTypeCode></nativeExtBox><itemSize Sync="TRUE">0.000</itemSize></itemProps><copyHistory><copy source="N:\Science\GISData\TOS\TOS_Plot_Data\14_DesertSW\REL1_JORN\Site_Information\14_R_JORN_Updated_Roads" dest="\\eco.neoninternal.org\neon\Science\GISData\TOS\TOS_Plot_Data\roads\14_R_JORN_Updated_Roads" date="20191204" time="22032600"/></copyHistory><coordRef><type Sync="TRUE">Projected</type><geogcsn Sync="TRUE">GCS_WGS_1984</geogcsn><csUnits Sync="TRUE">Linear Unit: Meter (1.000000)</csUnits><peXml Sync="TRUE">&lt;ProjectedCoordinateSystem xsi:type='typens:ProjectedCoordinateSystem' xmlns:xsi='http://www.w3.org/2001/XMLSchema-instance' xmlns:xs='http://www.w3.org/2001/XMLSchema' xmlns:typens='http://www.esri.com/schemas/ArcGIS/10.1'&gt;&lt;WKT&gt;PROJCS[&amp;quot;WGS_1984_UTM_Zone_13N&amp;quot;,GEOGCS[&amp;quot;GCS_WGS_1984&amp;quot;,DATUM[&amp;quot;D_WGS_1984&amp;quot;,SPHEROID[&amp;quot;WGS_1984&amp;quot;,6378137.0,298.257223563]],PRIMEM[&amp;quot;Greenwich&amp;quot;,0.0],UNIT[&amp;quot;Degree&amp;quot;,0.0174532925199433]],PROJECTION[&amp;quot;Transverse_Mercator&amp;quot;],PARAMETER[&amp;quot;false_easting&amp;quot;,500000.0],PARAMETER[&amp;quot;false_northing&amp;quot;,0.0],PARAMETER[&amp;quot;central_meridian&amp;quot;,-105.0],PARAMETER[&amp;quot;scale_factor&amp;quot;,0.9996],PARAMETER[&amp;quot;latitude_of_origin&amp;quot;,0.0],UNIT[&amp;quot;Meter&amp;quot;,1.0],AUTHORITY[&amp;quot;EPSG&amp;quot;,32613]]&lt;/WKT&gt;&lt;XOrigin&gt;-5120900&lt;/XOrigin&gt;&lt;YOrigin&gt;-9998100&lt;/YOrigin&gt;&lt;XYScale&gt;450445547.3910538&lt;/XYScale&gt;&lt;ZOrigin&gt;-100000&lt;/ZOrigin&gt;&lt;ZScale&gt;10000&lt;/ZScale&gt;&lt;MOrigin&gt;-100000&lt;/MOrigin&gt;&lt;MScale&gt;10000&lt;/MScale&gt;&lt;XYTolerance&gt;0.001&lt;/XYTolerance&gt;&lt;ZTolerance&gt;0.001&lt;/ZTolerance&gt;&lt;MTolerance&gt;0.001&lt;/MTolerance&gt;&lt;HighPrecision&gt;true&lt;/HighPrecision&gt;&lt;WKID&gt;32613&lt;/WKID&gt;&lt;LatestWKID&gt;32613&lt;/LatestWKID&gt;&lt;/ProjectedCoordinateSystem&gt;</peXml><projcsn Sync="TRUE">WGS_1984_UTM_Zone_13N</projcsn></coordRef><lineage><Process ToolSource="c:\program files (x86)\arcgis\desktop10.1\ArcToolbox\Toolboxes\Data Management Tools.tbx\Project" Date="20130530" Time="080908" Name="" export="">Project PrimaryRdsOnly C:\Users\pgroneme\Documents\ArcGIS\Default.gdb\PrimaryRdsOnly_Project PROJCS['WGS_1984_UTM_Zone_13N',GEOGCS['GCS_WGS_1984',DATUM['D_WGS_1984',SPHEROID['WGS_1984',6378137.0,298.257223563]],PRIMEM['Greenwich',0.0],UNIT['Degree',0.0174532925199433]],PROJECTION['Transverse_Mercator'],PARAMETER['false_easting',500000.0],PARAMETER['false_northing',0.0],PARAMETER['central_meridian',-105.0],PARAMETER['scale_factor',0.9996],PARAMETER['latitude_of_origin',0.0],UNIT['Meter',1.0]] # GEOGCS['GCS_WGS_1984',DATUM['D_WGS_1984',SPHEROID['WGS_1984',6378137.0,298.257223563]],PRIMEM['Greenwich',0.0],UNIT['Degree',0.0174532925199433],METADATA['World',-180.0,-90.0,180.0,90.0,0.0,0.0174532925199433,0.0,1262]]</Process><Process ToolSource="c:\program files (x86)\arcgis\desktop10.1\ArcToolbox\Toolboxes\AceTools.tbx\Merge" Date="20130530" Time="081027" Name="" export="">Merge PrimaryRdsOnly_Project;BTS_RdSubset_29May_Project1 D:\GIS_Stuff\JER_CDRRC_GIS_Data\Features_18Apr13.gdb\RdsMrg_30May13 "ObjectID "ObjectID" true true false 4 Long 0 0 ,First,#,PrimaryRdsOnly_Project,ObjectID,-1,-1;PRETYPE "PRETYPE" true true false 6 Text 0 0 ,First,#,PrimaryRdsOnly_Project,PRETYPE,-1,-1;NAME "NAME" true true false 30 Text 0 0 ,First,#,PrimaryRdsOnly_Project,NAME,-1,-1,BTS_RdSubset_29May_Project1,NAME,-1,-1;TYPE "TYPE" true true false 6 Text 0 0 ,First,#,PrimaryRdsOnly_Project,TYPE,-1,-1,BTS_RdSubset_29May_Project1,TYPE,-1,-1;CLASS_RTE "CLASS_RTE" true true false 1 Text 0 0 ,First,#,PrimaryRdsOnly_Project,CLASS_RTE,-1,-1;HWY_TYPE "HWY_TYPE" true true false 1 Text 0 0 ,First,#,PrimaryRdsOnly_Project,HWY_TYPE,-1,-1;HWY_SYMBOL "HWY_SYMBOL" true true false 20 Text 0 0 ,First,#,PrimaryRdsOnly_Project,HWY_SYMBOL,-1,-1;Shape_Length "Shape_Length" false true true 8 Double 0 0 ,First,#,PrimaryRdsOnly_Project,Shape_Length,-1,-1,BTS_RdSubset_29May_Project1,Shape_Length,-1,-1;PREFIX "PREFIX" true true false 2 Text 0 0 ,First,#,BTS_RdSubset_29May_Project1,PREFIX,-1,-1;FCC "FCC" true true false 3 Text 0 0 ,First,#,BTS_RdSubset_29May_Project1,FCC,-1,-1"</Process><Process ToolSource="c:\program files (x86)\arcgis\desktop10.1\ArcToolbox\Toolboxes\Data Management Tools.tbx\CalculateField" Date="20130530" Time="115046" Name="" export="">CalculateField RdsMrg_30May13 Label_1 [NAME] VB #</Process><Process ToolSource="c:\program files (x86)\arcgis\desktop10.1\ArcToolbox\Toolboxes\Data Management Tools.tbx\CalculateField" Date="20130530" Time="115117" Name="" export="">CalculateField RdsMrg_30May13 Label_1 "WSMR" VB #</Process><Process ToolSource="c:\program files (x86)\arcgis\desktop10.1\ArcToolbox\Toolboxes\Data Management Tools.tbx\CalculateField" Date="20130530" Time="115153" Name="" export="">CalculateField RdsMrg_30May13 Label_1 "" VB #</Process><Process ToolSource="c:\program files (x86)\arcgis\desktop10.1\ArcToolbox\Toolboxes\Data Management Tools.tbx\CalculateField" Date="20130603" Time="160407" Name="" export="">CalculateField Road HWY_TYPE "rd" VB #</Process><Process ToolSource="c:\program files (x86)\arcgis\desktop10.1\ArcToolbox\Toolboxes\Data Management Tools.tbx\CalculateField" Date="20130603" Time="160421" Name="" export="">CalculateField Road HWY_TYPE "R" VB #</Process><Process ToolSource="c:\program files (x86)\arcgis\desktop10.1\ArcToolbox\Toolboxes\Data Management Tools.tbx\CalculateField" Date="20130603" Time="160840" Name="" export="">CalculateField Road HWY_TYPE "R" VB #</Process><Process ToolSource="c:\program files (x86)\arcgis\desktop10.1\ArcToolbox\Toolboxes\AceTools.tbx\Append" Date="20130612" Time="083435" Name="" export="">Append 02175169_Jer2 RdsMrg_30May13 NO_TEST "PRETYPE "PRETYPE" true true false 6 Text 0 0 ,First,#;NAME "NAME" true true false 30 Text 0 0 ,First,#,D:\GIS_Stuff\JER_CDRRC_GIS_Data\AllRdLyrs\BTS_Rds_02175169\02175169_Jer2.shp,NAME,-1,-1;HWY_SYMBOL "HWY_SYMBOL" true true false 20 Text 0 0 ,First,#;FCC "FCC" true true false 3 Text 0 0 ,First,#,D:\GIS_Stuff\JER_CDRRC_GIS_Data\AllRdLyrs\BTS_Rds_02175169\02175169_Jer2.shp,FCC,-1,-1;Shape_Length "Shape_Length" false true true 8 Double 0 0 ,First,#;Label_1 "Label_1" true true false 20 Text 0 0 ,First,#;Label_2 "Label_2" true true false 30 Text 0 0 ,First,#" #</Process><Process ToolSource="c:\program files (x86)\arcgis\desktop10.1\ArcToolbox\Toolboxes\Data Management Tools.tbx\CalculateField" Date="20130612" Time="091132" Name="" export="">CalculateField RdsMrg_30May13 NAME [Label_1] VB #</Process><Process ToolSource="c:\program files (x86)\arcgis\desktop10.1\ArcToolbox\Toolboxes\Data Management Tools.tbx\CalculateField" Date="20130612" Time="091740" Name="" export="">CalculateField RdsMrg_30May13 Label_1 [NAME] VB #</Process><Process ToolSource="c:\program files (x86)\arcgis\desktop10.1\ArcToolbox\Toolboxes\Data Management Tools.tbx\CalculateField" Date="20130612" Time="092021" Name="" export="">CalculateField RdsMrg_30May13 Label_1 [NAME] VB #</Process><Process ToolSource="c:\program files (x86)\arcgis\desktop10.1\ArcToolbox\Toolboxes\Data Management Tools.tbx\CalculateField" Date="20130612" Time="092031" Name="" export="">CalculateField RdsMrg_30May13 Label_1 [NAME] VB #</Process><Process ToolSource="c:\program files (x86)\arcgis\desktop10.1\ArcToolbox\Toolboxes\Data Management Tools.tbx\CalculateField" Date="20130612" Time="093408" Name="" export="">CalculateField RdsMrg_30May13 Label_1 [NAME] VB #</Process><Process ToolSource="c:\program files (x86)\arcgis\desktop10.1\ArcToolbox\Toolboxes\Data Management Tools.tbx\CalculateField" Date="20130612" Time="093926" Name="" export="">CalculateField RdsMrg_30May13 Label_1 "Co_" VB #</Process><Process ToolSource="c:\program files (x86)\arcgis\desktop10.1\ArcToolbox\Toolboxes\Data Management Tools.tbx\CalculateField" Date="20130612" Time="093957" Name="" export="">CalculateField RdsMrg_30May13 Label_1 "Co_D" VB #</Process><Process ToolSource="c:\program files (x86)\arcgis\desktop10.1\ArcToolbox\Toolboxes\Data Management Tools.tbx\CalculateField" Date="20130612" Time="094008" Name="" export="">CalculateField RdsMrg_30May13 Label_1 "Co_E" VB #</Process><Process ToolSource="c:\program files (x86)\arcgis\desktop10.1\ArcToolbox\Toolboxes\Data Management Tools.tbx\CalculateField" Date="20130612" Time="094329" Name="" export="">CalculateField RdsMrg_30May13 Label_1 "" VB #</Process><Process ToolSource="c:\program files (x86)\arcgis\desktop10.1\ArcToolbox\Toolboxes\Data Management Tools.tbx\CalculateField" Date="20130612" Time="094340" Name="" export="">CalculateField RdsMrg_30May13 Label_1 "" VB #</Process><Process ToolSource="c:\program files (x86)\arcgis\desktop10.1\ArcToolbox\Toolboxes\Data Management Tools.tbx\CalculateField" Date="20130612" Time="094355" Name="" export="">CalculateField RdsMrg_30May13 Label_1 "" VB #</Process><Process ToolSource="c:\program files (x86)\arcgis\desktop10.1\ArcToolbox\Toolboxes\Data Management Tools.tbx\CalculateField" Date="20130612" Time="094416" Name="" export="">CalculateField RdsMrg_30May13 Label_1 "" VB #</Process><Process ToolSource="c:\program files (x86)\arcgis\desktop10.1\ArcToolbox\Toolboxes\Data Management Tools.tbx\CalculateField" Date="20130612" Time="120643" Name="" export="">CalculateField RdsMrg_30May13 Label_1 "" VB #</Process><Process ToolSource="c:\program files (x86)\arcgis\desktop10.1\ArcToolbox\Toolboxes\Data Management Tools.tbx\CalculateField" Date="20130612" Time="120739" Name="" export="">CalculateField RdsMrg_30May13 Label_1 "" VB #</Process><Process ToolSource="c:\program files (x86)\arcgis\desktop10.1\ArcToolbox\Toolboxes\Data Management Tools.tbx\CalculateField" Date="20130612" Time="120838" Name="" export="">CalculateField RdsMrg_30May13 Label_1 "" VB #</Process><Process ToolSource="c:\program files (x86)\arcgis\desktop10.1\ArcToolbox\Toolboxes\Data Management Tools.tbx\CalculateField" Date="20130612" Time="121009" Name="" export="">CalculateField RdsMrg_30May13 Label_1 "" VB #</Process><Process ToolSource="c:\program files (x86)\arcgis\desktop10.1\ArcToolbox\Toolboxes\Data Management Tools.tbx\CalculateField" Date="20130612" Time="122651" Name="" export="">CalculateField RdsMrg_30May13 HWY_SYMBOL "DA_Cty" VB #</Process><Process ToolSource="c:\program files (x86)\arcgis\desktop10.1\ArcToolbox\Toolboxes\Data Management Tools.tbx\CalculateField" Date="20130612" Time="122706" Name="" export="">CalculateField RdsMrg_30May13 HWY_SYMBOL "DA_Cty" VB #</Process><Process ToolSource="c:\program files (x86)\arcgis\desktop10.1\ArcToolbox\Toolboxes\Data Management Tools.tbx\CalculateField" Date="20130612" Time="123042" Name="" export="">CalculateField RdsMrg_30May13 HWY_SYMBOL "BTS" VB #</Process><Process ToolSource="c:\program files (x86)\arcgis\desktop10.1\ArcToolbox\Toolboxes\Data Management Tools.tbx\CalculateField" Date="20130612" Time="123130" Name="" export="">CalculateField RdsMrg_30May13 HWY_SYMBOL "BTS" VB #</Process><Process ToolSource="c:\program files (x86)\arcgis\desktop10.1\ArcToolbox\Toolboxes\Data Management Tools.tbx\CalculateField" Date="20130612" Time="123156" Name="" export="">CalculateField RdsMrg_30May13 HWY_SYMBOL "BTS" VB #</Process><Process ToolSource="c:\program files (x86)\arcgis\desktop10.1\ArcToolbox\Toolboxes\Data Management Tools.tbx\CalculateField" Date="20130612" Time="123206" Name="" export="">CalculateField RdsMrg_30May13 HWY_SYMBOL "BTS" VB #</Process><Process ToolSource="c:\program files (x86)\arcgis\desktop10.1\ArcToolbox\Toolboxes\Data Management Tools.tbx\CalculateField" Date="20130612" Time="123255" Name="" export="">CalculateField RdsMrg_30May13 PRETYPE "CtyRd" VB #</Process><Process ToolSource="c:\program files (x86)\arcgis\desktop10.1\ArcToolbox\Toolboxes\Data Management Tools.tbx\CalculateField" Date="20130612" Time="123404" Name="" export="">CalculateField RdsMrg_30May13 Label_1 "" VB #</Process><Process ToolSource="c:\program files (x86)\arcgis\desktop10.1\ArcToolbox\Toolboxes\Data Management Tools.tbx\CalculateField" Date="20130612" Time="123558" Name="" export="">CalculateField RdsMrg_30May13 Source "[HWY_SYMBOL] " VB #</Process><Process ToolSource="c:\program files (x86)\arcgis\desktop10.1\ArcToolbox\Toolboxes\Data Management Tools.tbx\CopyFeatures" Date="20130612" Time="160236" Name="" export="">CopyFeatures D:\GIS_Stuff\JER_CDRRC_GIS_Data\Features_18Apr13.gdb\RdsAllMrg_12Jun13 D:\GIS_Stuff\JER_CDRRC_GIS_Data\Infrastructure.gdb\RdsAllMrg_12Jun13 # 0 0 0</Process><Process ToolSource="c:\program files (x86)\arcgis\desktop10.1\ArcToolbox\Toolboxes\Data Management Tools.tbx\CopyFeatures" Date="20130613" Time="160027">CopyFeatures D:\GIS_Stuff\JER_CDRRC_GIS_Data\DataForJER_Portal_13Jun13.gdb\Roads_12Jun13 D:\GIS_Stuff\JER_CDRRC_GIS_Data\InfrastructureForPortal\Roads_12Jun13.shp # 0 0 0</Process></lineage></DataProperties><ArcGISProfile>FGDC</ArcGISProfile><ModDate>20130613</ModDate><ModTime>16002700</ModTime><ArcGISFormat>1.0</ArcGISFormat><scaleRange><minScale>50000</minScale><maxScale>5000</maxScale></scaleRange><SyncDate>20130613</SyncDate><SyncTime>16002700</SyncTime></Esri><dataIdInfo><dataExt xmlns=""><geoEle xmlns=""><GeoBndBox esriExtentType="search"><exTypeCode>1</exTypeCode><westBL Sync="TRUE">-107.251005</westBL><eastBL Sync="TRUE">-106.285983</eastBL><northBL Sync="TRUE">33.010540</northBL><southBL Sync="TRUE">32.197033</southBL></GeoBndBox></geoEle></dataExt><themeKeys xmlns=""><thesaName xmlns=""><resTitle>Jornada Theme Keywords</resTitle></thesaName><keyword>Road</keyword><keyword>Highway</keyword><keyword>Infrastructure</keyword><keyword>Transportation</keyword></themeKeys><placeKeys xmlns=""><thesaName xmlns=""><resTitle>Jornada Place Keywords</resTitle></thesaName><keyword>Jornada</keyword><keyword>Jornada Basin</keyword><keyword>Jornada Experimental Range</keyword><keyword>JER</keyword><keyword>JRN</keyword><keyword>Las Cruces</keyword><keyword>Dona Ana County</keyword><keyword>New Mexico</keyword><keyword>NM</keyword><keyword>Southwest</keyword><keyword>USA</keyword><keyword>Chihuahuan Desert</keyword></placeKeys><idCitation xmlns=""><datasetSeries><seriesName>knb-lter-jrn</seriesName></datasetSeries><presForm xmlns=""><fgdcGeoform>vector digital data</fgdcGeoform><PresFormCd value="005"/></presForm><resTitle>Roads_12Jun13</resTitle><citRespParty><rpOrgName>The Jornada</rpOrgName><role><RoleCd value="006"/></role><rpCntInfo><cntAddress addressType="physical"><delPoint>P.O. Box 30003, MSC 3JER</delPoint><city>Las Cruces</city><adminArea>NM</adminArea><postCode>88003</postCode><eMailAdd>gisdata@jornada-vmail.nmsu.edu</eMailAdd><country>UNITED STATES</country><delPoint> 2995 Knox Street, Room 200</delPoint></cntAddress><cntPhone><voiceNum tddtty="">575-646-4842</voiceNum><faxNum>575-646-5889</faxNum></cntPhone><cntHours>8 a - 5 p MST   M-F</cntHours><cntInstr>e-mail or call</cntInstr></rpCntInfo><displayName>The Jornada</displayName></citRespParty><citRespParty><rpOrgName>The Jornada</rpOrgName><role><RoleCd value="010"/></role></citRespParty><date><pubDate>2012-08-03T00:00:00</pubDate></date></idCitation><resMaint><maintFreq><MaintFreqCd value="011"/></maintFreq></resMaint><dataChar><CharSetCd value="004"/></dataChar><idStatus><ProgCd value="001"/></idStatus><dataLang><languageCode value="eng"/><countryCode value="USA" Sync="TRUE"/></dataLang><spatRpType><SpatRepTypCd value="001"/></spatRpType><idCredit>P. Gronemeyer
BTS 
Tiger
DA County Rd</idCredit><graphOver xmlns=""><bgFileName>filename.jpg</bgFileName><bgFileDesc>graphic showing the spatial extent of the research data collection with reference to Jornada boundaries and fences.</bgFileDesc><bgFileType>jpg</bgFileType></graphOver><resConst><SecConsts xmlns=""><class><ClasscationCd value="001"/></class></SecConsts><Consts xmlns=""><useLimit>&lt;DIV STYLE="text-align:Left;"&gt;&lt;DIV&gt;&lt;DIV&gt;&lt;P&gt;&lt;SPAN&gt;While substantial efforts are made to ensure the accuracy of data and documentation, complete accuracy of data/spatial data layers cannot be guaranteed. All data are made available "as is". The Jornada (United States Department of Agriculture, Agricultural Research Service, Jornada Experimental Range and the Jornada Long-Term Ecological Research program) shall not be liable for damages resulting from any use or misinterpretation of data.&lt;/SPAN&gt;&lt;/P&gt;&lt;DIV STYLE="font-size:12pt"&gt;&lt;P&gt;&lt;SPAN /&gt;&lt;/P&gt;&lt;P&gt;&lt;SPAN /&gt;&lt;/P&gt;&lt;/DIV&gt;&lt;/DIV&gt;&lt;/DIV&gt;&lt;/DIV&gt;</useLimit></Consts></resConst><idAbs>&lt;DIV STYLE="text-align:Left;"&gt;&lt;DIV&gt;&lt;DIV&gt;&lt;P&gt;&lt;SPAN&gt;Road layer of JER, CDRRC and area around boundaries, created from taking what are hopefully driveable roads from any road layer that found, including NM Hwy, Tiger Rds, BTS, etc.. Note that Source Field in table is where the name of the road was verified. DaCty is from http://maps.donaanacounty.org/maps/; BTS is Bureau of Transportation Statistics. Mostly major roads that had official names have sources. Roads &amp;lt;200m long were merged with other roads whenever possible. "Unnamed roads" with the &lt;/SPAN&gt;&lt;SPAN STYLE="font-weight:bold;"&gt;same&lt;/SPAN&gt;&lt;SPAN&gt;FCC code were merged whenever possible.&lt;/SPAN&gt;&lt;/P&gt;&lt;P&gt;&lt;SPAN&gt;\\\\\For display purposes the following files may be useful: &lt;/SPAN&gt;&lt;/P&gt;&lt;P&gt;&lt;SPAN&gt;PrimaryRdsOnly: For main highways and interstates _only_ &lt;/SPAN&gt;&lt;/P&gt;&lt;P&gt;&lt;SPAN&gt;Rds_OffJer_12Jun13 for roads surrounding but NOT including JER and CDRRC (for map display, make this layer lighter and thinner than roads w/in boundaries).&lt;/SPAN&gt;&lt;/P&gt;&lt;P&gt;&lt;SPAN&gt;RdsInBndrys_12Jun13 for roads only within JER and CDRRC boundaries. &lt;/SPAN&gt;&lt;/P&gt;&lt;/DIV&gt;&lt;/DIV&gt;&lt;/DIV&gt;</idAbs><idPoC xmlns=""><rpPosName>GIS Administrator</rpPosName><role><RoleCd value="007"/></role><rpCntInfo xmlns=""><cntAddress addressType="physical"><delPoint>P.O. Box 30003, MSC 3JER</delPoint><city>Las Cruces</city><adminArea>NM</adminArea><postCode>88003</postCode><eMailAdd>gisdata@jornada-vmail.nmsu.edu</eMailAdd><country>UNITED STATES</country><delPoint> 2995 Knox Street, Room 200</delPoint></cntAddress><cntPhone><voiceNum tddtty="">575-646-4842</voiceNum><faxNum>575-646-5889</faxNum></cntPhone><cntHours>8 a - 5 p MST   M-F</cntHours><cntInstr>e-mail or call</cntInstr></rpCntInfo><rpOrgName>The Jornada</rpOrgName></idPoC><idPurp>Layer of primary/secondary roads and highways in and around JER and CDRRC.  Part of basic infrastructure to aid in navigation and site selection.  </idPurp><resConst><LegConsts xmlns=""><useLimit>This dataset is released to the public and may be used for academic, educational, or commercial purposes subject to the following:
Please send notification to the Information Manager of the data sets downloaded and their intended use. Please acknowledge data set source using the following statement: This material is based upon work supported by the United States Department of Agriculture, Agricultural Research Service, Jornada Experimental Range and Jornada Basin Long-Term Ecological Research (JRN LTER) program with funding by the USDA and the National Science Foundation (NSF Grant DEB-0618210). Please send 1 copy of any publication that cites Jornada data sets to: DataManager@jornada-vmail.nmsu.edu or DATA MANAGER Jornada Experimental Range P.O. Box 30003, MSC 3JER New Mexico State University Las Cruces, NM 88003-0003
</useLimit></LegConsts></resConst><themeKeys xmlns=""><thesaName><resTitle>LTER Core Research Areas</resTitle></thesaName></themeKeys><searchKeys><keyword>Road</keyword><keyword>highway</keyword><keyword>primary</keyword><keyword>secondary</keyword><keyword>County</keyword><keyword>interstate</keyword></searchKeys><envirDesc Sync="TRUE">Microsoft Windows 7 Version 6.1 (Build 7601) Service Pack 1; Esri ArcGIS 10.1.1.3143</envirDesc><tpCat><TopicCatCd value="013"/></tpCat><tpCat><TopicCatCd value="018"/></tpCat><tpCat><TopicCatCd value="003"/></tpCat></dataIdInfo><mdContact xmlns=""><rpPosName>GIS Administrator</rpPosName><role><RoleCd value="007"/></role><rpCntInfo xmlns=""><cntAddress addressType="physical"><delPoint>P. O. Box 30003, MSC 3JER</delPoint><city>Las Cruces</city><adminArea>NM</adminArea><eMailAdd>gisdata@jornada-vmail.nmsu.edu</eMailAdd><country>UNITED STATES</country><delPoint>2995 Knox Street, Room 200</delPoint><postCode>88005</postCode></cntAddress><cntPhone><voiceNum tddtty="">575-646-4842</voiceNum><faxNum>575-646-5889</faxNum></cntPhone><cntHours>8 a - 5 p MST  M-F</cntHours><cntInstr>e-mail or call</cntInstr></rpCntInfo><rpOrgName>The Jornada</rpOrgName></mdContact><mdMaint><maintFreq><MaintFreqCd value="011"/></maintFreq></mdMaint><mdChar><CharSetCd value="004"/></mdChar><mdHrLv><ScopeCd value="005"/></mdHrLv><mdConst><SecConsts xmlns=""><class><ClasscationCd value="001"/></class></SecConsts></mdConst><mdConst><Consts xmlns=""><useLimit>&lt;DIV STYLE="text-align:Left;"&gt;&lt;DIV&gt;&lt;DIV&gt;&lt;P&gt;&lt;SPAN&gt;Data re-use, distribution and production of derivative products are governed by the Jornada data policies (http://jornada.nmsu.edu/lter/data/data-policies). Our data policies comply with the LTER Network data policies (http://www.lternet.edu/data/netpolicy.html) in the spirit of having the potential to increase communication, collaboration and synthesis within and among disciplines. Appropriate citation, acknowledgment, notification and collaboration are outlined and recommended in the Jornada data policies. No commercial redistribution of data and derived products are allowed. While substantial efforts are made to ensure the accuracy of data and documentation, complete accuracy of data/spatial data layers cannot be guaranteed. All data are made available "as is". The Jornada (United States Department of Agriculture, Agricultural Research Service, Jornada Experimental Range and the Jornada Long-Term Ecological Research program) shall not be liable for damages resulting from any use or misinterpretation of data.&lt;/SPAN&gt;&lt;/P&gt;&lt;/DIV&gt;&lt;/DIV&gt;&lt;/DIV&gt;</useLimit></Consts></mdConst><distInfo><distTranOps><onLineSrc><linkage>http://jornada.nmsu.edu/sites/default/files/shapefile_packages/filename_shp.zip</linkage><orFunct><OnFunctCd value="001"/></orFunct></onLineSrc><transSize Sync="TRUE">0.000</transSize></distTranOps><distFormat><fileDecmTech>unzip</fileDecmTech><formatVer>ArcGIS 10.1</formatVer><formatName>File Geodatabase Feature Class</formatName></distFormat><distributor><distorCont><rpOrgName>The Jornada</rpOrgName><role><RoleCd value="005"/></role><rpCntInfo><cntAddress addressType="physical"><delPoint>P.O. Box 30003, MSC 3JER</delPoint><city>Las Cruces</city><adminArea>NM</adminArea><postCode>88003</postCode><eMailAdd>gisdata@jornada-vmail.nmsu.edu</eMailAdd><country>UNITED STATES</country><delPoint>2995 Knox Street, Room 200</delPoint></cntAddress><cntPhone><voiceNum tddtty="">575-646-4842</voiceNum><faxNum>575-646-5889</faxNum></cntPhone><cntHours>8 a - 5 p MST M-F</cntHours><cntInstr>e-mail or call</cntInstr></rpCntInfo></distorCont></distributor></distInfo><dqInfo><dataLineage><prcStep><stepDesc>Data collection locations were gps'd using Trimble mapping grade equipment. These data were processed using differential correction for submeter accuracy, then exported to a spatial layer. The spatial layer was then verified and the attribute table created. The spatial layer was then verified to be relatable to the associated data table.</stepDesc></prcStep></dataLineage><dqScope><scpLvl><ScopeCd value="005"/></scpLvl></dqScope></dqInfo><mdConst><LegConsts xmlns=""><useLimit>This dataset is released to the public and may be used for academic, educational, or commercial purposes subject to the following:
Please send notification to the Information Manager of the data sets downloaded and their intended use. Please acknowledge data set source using the following statement: This material is based upon work supported by the United States Department of Agriculture, Agricultural Research Service, Jornada Experimental Range and Jornada Basin Long-Term Ecological Research (JRN LTER) program with funding by the USDA and the National Science Foundation (NSF Grant DEB-0618210). Please send 1 copy of any publication that cites Jornada data sets to: DataManager@jornada-vmail.nmsu.edu or DATA MANAGER Jornada Experimental Range P.O. Box 30003, MSC 3JER New Mexico State University Las Cruces, NM 88003-0003
</useLimit></LegConsts></mdConst><mdLang><languageCode value="eng"/><countryCode value="USA" Sync="TRUE"/></mdLang><mdDateSt>20130418</mdDateSt><mdHrLvName Sync="TRUE">dataset</mdHrLvName><refSysInfo><RefSystem><refSysID><identCode code="32613" Sync="TRUE"/><idCodeSpace Sync="TRUE">EPSG</idCodeSpace><idVersion Sync="TRUE">7.11.2</idVersion></refSysID></RefSystem></refSysInfo><spatRepInfo><VectSpatRep><geometObjs Name="Roads_12Jun13"><geoObjTyp><GeoObjTypCd value="002" Sync="TRUE"></GeoObjTypCd></geoObjTyp><geoObjCnt Sync="TRUE">0</geoObjCnt></geometObjs><topLvl><TopoLevCd value="001" Sync="TRUE"></TopoLevCd></topLvl></VectSpatRep></spatRepInfo><spdoinfo><ptvctinf><esriterm Name="Roads_12Jun13"><efeatyp Sync="TRUE">Simple</efeatyp><efeageom code="3" Sync="TRUE"></efeageom><esritopo Sync="TRUE">FALSE</esritopo><efeacnt Sync="TRUE">0</efeacnt><spindex Sync="TRUE">FALSE</spindex><linrefer Sync="TRUE">FALSE</linrefer></esriterm></ptvctinf></spdoinfo><eainfo><detailed Name="Roads_12Jun13" xmlns=""><enttyp><enttypl Sync="TRUE">Roads_12Jun13</enttypl><enttypt Sync="TRUE">Feature Class</enttypt><enttypc Sync="TRUE">0</enttypc></enttyp><attr><attrlabl Sync="TRUE">FID</attrlabl><attalias Sync="TRUE">FID</attalias><attrtype Sync="TRUE">OID</attrtype><attwidth Sync="TRUE">4</attwidth><atprecis Sync="TRUE">0</atprecis><attscale Sync="TRUE">0</attscale><attrdef Sync="TRUE">Internal feature number.</attrdef><attrdefs Sync="TRUE">Esri</attrdefs><attrdomv><udom Sync="TRUE">Sequential unique whole numbers that are automatically generated.</udom></attrdomv></attr><attr xmlns=""><attrlabl Sync="TRUE">Shape</attrlabl><attalias Sync="TRUE">Shape</attalias><attrtype Sync="TRUE">Geometry</attrtype><attwidth Sync="TRUE">0</attwidth><atprecis Sync="TRUE">0</atprecis><attscale Sync="TRUE">0</attscale><attrdef Sync="TRUE">Feature geometry.</attrdef><attrdefs Sync="TRUE">Esri</attrdefs><attrdomv><udom Sync="TRUE">Coordinates defining the features.</udom></attrdomv></attr><attr xmlns=""><attrlabl Sync="TRUE">PRETYPE</attrlabl><attalias Sync="TRUE">PRETYPE</attalias><attrtype Sync="TRUE">String</attrtype><attwidth Sync="TRUE">6</attwidth><atprecis Sync="TRUE">0</atprecis><attscale Sync="TRUE">0</attscale><attrdef>Used as category field for labeling - depending on map and scale.  Can use HwySymbol also.</attrdef></attr><attr xmlns=""><attrlabl Sync="TRUE">NAME</attrlabl><attalias Sync="TRUE">NAME</attalias><attrtype Sync="TRUE">String</attrtype><attwidth Sync="TRUE">30</attwidth><atprecis Sync="TRUE">0</atprecis><attscale Sync="TRUE">0</attscale><attrdef>One version of road name, assumed to be correct because came from offiical layers.   Usually too long to use as label, so see label fields</attrdef></attr><attr xmlns=""><attrlabl Sync="TRUE">HWY_SYMBOL</attrlabl><attalias Sync="TRUE">HWY_SYMBOL</attalias><attrtype Sync="TRUE">String</attrtype><attwidth Sync="TRUE">20</attwidth><atprecis Sync="TRUE">0</atprecis><attscale Sync="TRUE">0</attscale><attrdef>Used as category field for labeling - depending on map and scale.  Can use PRETYPE also.</attrdef></attr><attr xmlns=""><attrlabl Sync="TRUE">FCC</attrlabl><attalias Sync="TRUE">FCC</attalias><attrtype Sync="TRUE">String</attrtype><attwidth Sync="TRUE">3</attwidth><atprecis Sync="TRUE">0</atprecis><attscale Sync="TRUE">0</attscale></attr><attr xmlns=""><attrlabl Sync="TRUE">Label_1</attrlabl><attalias Sync="TRUE">Label_1</attalias><attrtype Sync="TRUE">String</attrtype><attwidth Sync="TRUE">20</attwidth><atprecis Sync="TRUE">0</atprecis><attscale Sync="TRUE">0</attscale><attrdef>recommended, standard way to label roads that have names, esp county roads.  Usually shorter and more consistent than "name" field</attrdef></attr><attr xmlns=""><attrlabl Sync="TRUE">Label_2</attrlabl><attalias Sync="TRUE">Label_2</attalias><attrtype Sync="TRUE">String</attrtype><attwidth Sync="TRUE">30</attwidth><atprecis Sync="TRUE">0</atprecis><attscale Sync="TRUE">0</attscale><attrdef>alternative label/name given only when available</attrdef></attr><attr xmlns=""><attrlabl Sync="TRUE">Source</attrlabl><attalias Sync="TRUE">Source</attalias><attrtype Sync="TRUE">String</attrtype><attwidth Sync="TRUE">8</attwidth><atprecis Sync="TRUE">0</atprecis><attscale Sync="TRUE">0</attscale><attrdef>Source from which name and location of road was verified. DaCty is from http://maps.donaanacounty.org/maps/; BTS is Bureau of Transportation Statistics. Mostly major roads that had official names have sources</attrdef></attr><attr><attrlabl Sync="TRUE">Shape_Leng</attrlabl><attalias Sync="TRUE">Shape_Leng</attalias><attrtype Sync="TRUE">Double</attrtype><attwidth Sync="TRUE">19</attwidth><atprecis Sync="TRUE">0</atprecis><attscale Sync="TRUE">0</attscale></attr></detailed></eainfo><Binary><Thumbnail><Data EsriPropertyType="PictureX">/9j/4AAQSkZJRgABAQEAAQABAAD/2wBDAAgGBgcGBQgHBwcJCQgKDBQNDAsLDBkSEw8UHRofHh0a
HBwgJC4nICIsIxwcKDcpLDAxNDQ0Hyc5PTgyPC4zNDL/2wBDAQkJCQwLDBgNDRgyIRwhMjIyMjIy
MjIyMjIyMjIyMjIyMjIyMjIyMjIyMjIyMjIyMjIyMjIyMjIyMjIyMjIyMjL/wAARCACFAMgDASIA
AhEBAxEB/8QAHwAAAQUBAQEBAQEAAAAAAAAAAAECAwQFBgcICQoL/8QAtRAAAgEDAwIEAwUFBAQA
AAF9AQIDAAQRBRIhMUEGE1FhByJxFDKBkaEII0KxwRVS0fAkM2JyggkKFhcYGRolJicoKSo0NTY3
ODk6Q0RFRkdISUpTVFVWV1hZWmNkZWZnaGlqc3R1dnd4eXqDhIWGh4iJipKTlJWWl5iZmqKjpKWm
p6ipqrKztLW2t7i5usLDxMXGx8jJytLT1NXW19jZ2uHi4+Tl5ufo6erx8vP09fb3+Pn6/8QAHwEA
AwEBAQEBAQEBAQAAAAAAAAECAwQFBgcICQoL/8QAtREAAgECBAQDBAcFBAQAAQJ3AAECAxEEBSEx
BhJBUQdhcRMiMoEIFEKRobHBCSMzUvAVYnLRChYkNOEl8RcYGRomJygpKjU2Nzg5OkNERUZHSElK
U1RVVldYWVpjZGVmZ2hpanN0dXZ3eHl6goOEhYaHiImKkpOUlZaXmJmaoqOkpaanqKmqsrO0tba3
uLm6wsPExcbHyMnK0tPU1dbX2Nna4uPk5ebn6Onq8vP09fb3+Pn6/9oADAMBAAIRAxEAPwD3+iii
gAooooAKKKxvEutDRdInliKm9aJzbRsjOGZRnJC/wjqTwAO4qoQc5KK3YGzRXAReK9audO1bUIxa
XVtZ280YbTpFZFlVdwkYuQGXbggIxI3EMCemtaalr0s99aQWsYeALPCL98SyRtnAIQbV+ZHAOSQM
ZUdDvLCzju19/wDXcXMdTRXO3XiQsUs7dEtdVaSNTa3o5CsSN3ythlyCNykjP5VF4l1TWLDQJruO
3ERNuwfyjvaCXPDZ6Mh5GcAjgkAZ2wqEm0trhc6emtLGjojOqu5IRScFsDJx68V5peeJr26vdFcX
U0KStFbtp8MqLeAyRsRMw37R86ou1wwwSTgkY0Lt/E/9oR3t/BJDp9rE8RlhWIXUm8ochfMZBjYF
yOTu+VR1GzwjVuaSQuY72iuJGv6/byabps1tGb2S3USpGwklSQbTmQ5CKGUSnA3E7SR3x0DM1t4p
gjFxJ5V5bSu0Lvld6GIAoD935WbIHBxnGck4yoOO77/gO5rUUjMqIWZgqqMkk4AFZt3rtnbkRQs1
5dMMpb2o8xm9M44QH+8xA96zjFy2QzTorkm8VajD4pOnT6JdCFNPNwyReXI5bftyMPyvGBwDk8gd
tC18VWc0W+7tNR0759h+22ckajJwCXwUAPu3XitJYeole1/TUV0a1vd292HMEofYzKw6EFWZDx/v
Kwz3xU9cZ4dvGk1u3cWkscV1HeOJgyskym43pnByCodwQwGCxHPNdnSq0/ZysCdwooorIYUUUUAF
FFFABRRRQAUUUUAFZHiDR59ZtYY7e7S1lil3iRoi+VwQy8Mp5BIPPf1wRr1l67dm1swBqllpokJU
3F0R8vB+6CQC3fk446GtKTkprl3EzETwZeCGVJNaD+d5fnw/ZAIbnaoXMqhtzZUKCFdVOOVOTnkL
vU9S8M6i9z9hnEtvevbiKyljSB4toIRYXdmTP7pyVGApJyvQdt4Vu7/UtDvrbUb1LsQSNbR6lBFs
FygUZcKwKkgkjIypKnHcVx3hyx0ERSR/208Nnc2TWs8rRQJFKqu6bQzR7cMoJODk8Z7V6VGUk5qp
ql5f5eRD8jS8V+KJvsdlNf8Ahu7s7eO9gkW5neMPCRKh6DIAKhlJBJGehHIf4h1F/E1vPbFLmzst
kfkMxlRZy8xQecqYZVby2UDkkSZ4Iqt4Tv8AR/Ed3FpMOl2P2iwdjfXdvAnlTrGQE2sBzvba2OmE
b1FbXm6VZ3ZttRiF3qmjr/og8oNLNERmI9PvZBXOR8yE8ZoajSaio2lHX+v663sG559e2OreYmrR
RtNpk1wp064juni2IIGaParKCygjK8bjgKC2c130KweJp7aGw1DVjbRGK7uHn3x/L96NVDKCSWAb
OCML7ijT9Cvbq7j02/uPsi6TJ9stRalJQxlMm0kyIcbPnReO27jgCzoui3kNxceVrE4ltXe1KvBG
w2bvMjHCjojrj03N9AVq8ZLezW36fhb5sEircWV5Bc309lFJcSadqP2vzJpyC+LaIMmB95mRmUE8
LnPtV7X9d0+3Og30tyqqtys5iHzyeW8MiA7VySAZByOOOtV0F5d3Gu6HDO73E1yBc3irsEEbQRDI
7byMhR2xk9gdpLDRvDuhTROkUNgkQWZpTu3rtC4YnrxgY/AVzykly82r8uzX9W0KGRWM2ryxXmqw
qsKgmGxb5gpJUh5OxcbeABhcnk9a0RZpbW0kenx29q7A7SIRtB9SoIz+dc9a2niNtBtme5FrPaWy
mKFDva5dV484spwDwCq5IJPzHiri+Il1LT1l0WGa5lkjV1dIQ8aEjOCS6KSO4DZFZThJ7PRfchmU
TcaX8SLSTUp/NjvbBrW3nEWxd4ffsYgkZ9OmdwABwTWv4vvbWy8K6l9qlWJZraWJWf7pYxtgE9Bn
GBnqcDqQK5Tx2usXngK6udVjt7QW8sbJGkReUt5gUOCrkLkN0+bgnkduji8N3s16JtY1K31SINkQ
z2ZCoO21Q+zIP8RUt71tKMLQqTe2mnW1tunUnyKPgu4n1fUNT1WZY0gSaSK2RCGK7ny+WBKtkLF9
3IGDyea7KiiuSrU9pLmSsUlYKKKKzGFFFFABRRRQAUUUUAFFFFABVDVNLh1JYDKQrQSiQMVDAr0d
CDwVZcg/geoFXJokngkhkzskUq21ipwRg4I5H1FcyWur69tfDmobnMSma5lIwt1CuAnPqzEb1x/C
w6MpOtKLbunawmZnhiz11LK91CyndbRpXfT7O5l8xJYdxKgf88xjAUgng5IIwKgkQG4stK8M3AtN
O1RfPuUkVmEDMWcAAMGUybJVYBhgrxtJJOrceIbuHXpZQbcaLDcJYNKZeI5Mb5HcY6fdReRhs5GO
QaZ4V0hr7WYxHcqsd8u0JezLg+TE+eH65YnPXmu32lm5z0vqra/f5q9ybDk0BG8S3cdvdS2CrYwb
lsAsQcsZFbghsfLFGBjBXbweauXWi2+nFtUh1K+tmghYMzym4BTgkESbmP3RwCP1rD8RtrHhdn1i
1b7RaW7iONJd08rJIFXZksPl8wIQSSRuP0OlOmr3xsbm41DR/szlJLeEbwkkvVCSTmTHBUALzzgk
DENSaUubR/1YZR8Ny+JoPFJHiG3t0S8tNkc8RGXaMhgrDON2JJOgH3fbJ35J49O1m/eWeK2hmtFn
EkpwgZCVdm5HABi71yl0fFfiDWb63SRbMaLNvjltwuyeQx5VAXUkMVfBbOAGxgk5Gt/Z+kXEui6r
Gst3EZ2iZr2Z5/K3qwxtcnY/mKikDGDkfR1YpvmlbVbL719+gkc7a6lLqN3d6nEkWj3k0/mRX9ws
iR3QVFRUQkKJI2KZ+fkBvlUn5q6WW81rXdH0+6t9JtvIke3uypvPmZAyyAAFAM4A6kc8dOa6jdFM
HjyjjGGXg+2CPzpyqFUKoAAGAB2rGeIi2mo7bDSKen6pBqPmoiyRXEJCzW8oAkiJ6ZAJGDjggkHs
TVTw75cFncaeuEezupUMX9xGcvGB7bGXH5dqzfE0M8F4jaVNHFfanE9kyGQqSSvyTADOTHg846N1
4FWpb200jxNOLmURi6s4RAmC7ytG0gYKoyzEB04APc0vZ3h7vXW3p/TC5F8QLee58DanHbpvcKjk
Zx8qyKzHqOign8K6C2uIru1iuYW3RSoHQ4xkEZFUpr+a4s0az02a5EwYbbgeQqj/AGw43AH2U/Ss
LwEbm2t9U0m4REWwvGSJUk3qqN8wUMQCcZ6kZJz2wAcrdFp/Zd/vsv0Q+p19FFFcwwooooAKKKKA
CiiigAooooAKKKKACua8W/2rBAmoaZ5Ae3VsSMhLRbhgkjPzJ0JHGCob5sYrparahZ/b7N7bz5YF
cjc8LFX25BIDDkZHGRzzxg81pSlyzTYmcNe+PNI8K6OlrcaZqBeSHzFJiSRJ2cMQWkRip3lW75OD
xVm08W+HtD0S3hs7y2urwQoJI03q0xijUMcbSdwVRwQOgHFcHonw103xdeM91B9nt0tUV7jT5V2+
cEiK7htA3lXYsMHBzljkVvS/C6fwk0OteFtVvBfQRiOdWtIp2mjAC/InyDcAB3ycdSevrzpYNe45
Pme/ZvpfexmnLc0Nc19PGhi0HRbmdUvLdmuNrwAmPK5Chju3YzyM7e4OQRmaHLqWkQwSi1tFvkkG
mmS6umaX97JsQopTASN1kXYpUFUbjIFbWg+JrXxtaSaLrUQ0vxJbMWERXZIjqcrNEH57A45465Fc
raDX9S1meCcpb3dncbJ2eIRx5mmd4mCHc5VuME7SpkkGe1FONouk0kl38+t+qe33A+56dollDpWq
ajp9uG2FYbpmY7i7vuRmYnqxMWT9fesHxPoz6tc6jLpskls+nos8ghkdRc3IAdVYKwG4KF+bBOWX
qFwdi01SK88UQLtkt7n7JLHcW8owyMHQrj1B/eYYcHHtV3SSDqGuMvQ3w5HfEEIP6jH4VwKc6c/a
dbL9EXvoeUaTYzWOs3MVrf6jpU0xkRzGEuJbpjskhVW6sCHZg52/xhujEbmj6t4l1iPSrmDWZZYr
+3CG6js1hiilI3AfOG8zAEmSqgEhVyueJNY0bSFbQb/VTJHbWVw+mXTK7IpjQSLC0uCOMgdc/wCt
x0NT6HZXN/8AD/TNK8PotsEiik/tGSNRFvXBBCjmVsgZYYXIzuOMHvqVIyjzNeV2lbr13fR29CEj
e1mW28KaPLdw3Cf2ncMsaXF4Q7TyddrEsoAwG4BVVycDsWeHdWt9ak/tm6u4Y5vL8uC1MihoI3Eb
HeOoYlR3IwBjvnBlOrx+FTqlvY2k+p6hEIlmuLx5J98g2lEXylCYPJVcAbSSOM129pHpl/ptndpB
byQLErws6hvLAHGCemK4qiUIa6u9r/p/XmWtWaNcp4SmWfWPEsiLIq/bQB5iFD90diAa27vWrO10
xL7zPNSWMPbxx/fnyMqqKepORge9Yltd6hba5aXt7o8WnRaiPs9won8x/NAJRm2rtxwyglsncvAx
isacXySVt/01G9zq6KKK5xhRRRQAUUUUAFFFFABRRRQAUUUUAFIRlSMkZHUUtFAHm2najceAl0/S
Wsp9SW8ia4lS1h3S27AD5fkBEhIU46H925ye3Wavq9xH4bm1C2aKwIDEPqKldowdp2jnJO0AHnno
T8pxoNDOurqE0L6WLJ7qZYEuLJLpo2ViHYHIADOC20hvXPzYGT5hsNTvdE1DRzrMllC0tpLKiuTE
qptKwHbHkbyvyFS2xuAc16cowqyv9pav+np5f5kao4LWbHZqOnappdzNf626J9sjO4SG4Zw3yMDu
woZhlAeAOv8AD0evtH4dkttXt9H1eA6haPb3j3UjyM7EBlYMWYq6sM/ORwvAxk11E8/ib+wtPmsd
D01oLfF2i2cwCzAEkAJ0jBBJyrSYJH3uTVDxjo2i+MNCu9Z0ow6jf7bdW8ubf5KhjuABHGQzBgcD
5c8FTXYsRzSip7are/pe1ku6Jt2MvXPF99rGmaVq7eHMQ25eZruKV/lA/dv867TGo3Fj8xztUc84
1vDksgDT6v4nl0+yeSSa0txOgilRyX3i4KjzMliccMOM46Hm/CL62dHudLivSdEnkura4v5IA4Eu
3aNgQnCkbfvBeSeSQN2rfLpkOu290s9nrVnHP/plhab4vsjsjKJyjOY0+8dxOzkBgcg0VIQV6UV3
tbX89EwT6kXiBNAvYtdtRdve2ksIuI5BdyTtcyGMRoiYJyodNzMvAIUHgEDPkhXRtGebWLrSVjQs
1pLp8q+aQAHjYyDMrIPuE5DDvvDcbFxa3Xh2+t49K0e7fT9Q8mN0uJYN+1Jo9irIJCWGHKgNkgdD
gcRx6nZPaapBf20yas9+0K6WkHmLbs5LGTagPnFQXkyc9BgKTThJ8q5dY+uvb5eb2/ADR0+fy9S1
K80vVre40/TIjfQWszC5YCVS0jBg4ZXyJB8xb754AOTY0CxkS/OgaxDthcPKtraOPIBPzMkgVFyV
V487mYNvXAODjoLnTfD+r/ZpZ5LC7tYLR4ykuyRTGQp3Z7YC9fRj61xPhe98P/Y/Dl+9nApiklW5
v2iCRmUrIQd7Ku4/uzgAHbkDg4zyqXtISaT+7VOztr8n949mdd4R0WwsDdn7MP7RtbiS2eZxlvLw
nlgHH3fKEWBzjB5JyTmfED/hIE8NNOl0sRN3ABb2kPmYXeuCzsM53fxADHH1O1p2p2154lvp7WO5
CfYYmn8y2eM8M+whWAZsgtyAc7cdRisfx1rFtdaHHDFc3ttILy0IiltXhWcG5jBGZEBOOuFIPrxW
NLneJi2r7b9P8hu1ju6wfEWqz28lnpVgjvfX8nlhlOPJjGS7k9AdobbnqfXBrWvr2DTrKW7uX2xR
jJ9STwAB3JJAA7kiuc8KkazdzeI2kEqzRiKJ1zjrllXPVVwqg/3lkP8AFXNSjZOpJaL8yn2Ont4I
7W3it4V2xRIERc5woGAOakoorDcYUUUUAFFFFABRRRQAUUUUAFFFFAHCalpU/gbT7vUfDFv5zPDm
4t5IQwkMYP70uCpD4JJOGL7RxuOTXfQtO13w1o2rl7T7M8KPKbi2a4luZHwqMzxurFskjHI+cjHA
xqalfa1pD3cd7dWU1m0E9yjywMuVUszRFg/BVNuDt+YBumOeB0mbXdFtU0hW06GzEaazZWEkjF3X
zSwiGATy4QgdV3YO7FevRjOceZS96+/df8Azdjpvt93Y2sfhu6stPv20+eKwgVr17c3WYYyreV82
8AMd25sfKcZIxS6/pGtaxHevpF5ePdoClxLBL9mim2K4W3jBzwrklmz3YZJ4Xprzw8L5rfUL/UHt
7uCL95JBHEEGGD5/eI+MFV5z/CKpalpE+k6Vt/te+fS1naW9GyLzBGxZnbcFHAY7jgZxux2rKNaN
042v87P+u2g7HL+GvEPk2esWtjbf2dd2tzHePp4iA2QosccsKruPKqmSeCd4IXkZ7fxC1rLarBLq
Fta212p87vLcRjA2pg5OdwBxk4bAwSDXD+NfDWr6Z4sHifSctbvIjzuArC1+XZI5QkbkKhSQCOjZ
4OQzw9Enh/xK7a1pUh1RFWCwiSQy4Rn2hzJI2Bw6RgjsCBk5A2nTp1Eq0Hra9ut9NNe3fX8hJtaM
fqviZJ/h4s9tDqGoPpzZS8W0ZUKhSFlYYyF8pi+du3jBPc4v2y+1DxZeahdaVdW2mJqCxtKJLgSR
t5sPmAeUCM8IOSvcjJxXUeKPDmk3U9jfvptteJsGnS2UFzKBEwXgR+Upb5BvyAo4JOBiue0rTb3V
vCNi9tbQxWv2iBbsi4KJdSmdMAwtCyYUnGcHooydpWt6MqahzRVrvr0v8/Lt1E73IvFk+na3p1vB
4U0mEaeQ8UtxBbhnKlkBJXGY8kcSN83DYBByfRvDd9qdxoOmyWWgWNpYSRI0aNfYKxEAhgqxY5Bz
jj3xVfVL5dH8LXEOr3QhYbfK8+WIswBHCrGq5Ax0C5rk9blvdL8F3+of2fq0MduhXS5XkDC2hACL
8ispXgkhmUkDg5wM4fx4Knbro273v91x7O50HiHxLN4f8XGaCCzvzc2YjjiRmjlDLIVVSw3bwXZh
gLlSemNxEHj7Wmu/hrb3S2gS81KWL7FE4ZyjMd6sdvIYICfZumcDNHUfB3ibUEnsJ7TSyL25N7Lf
W9w0QhlAwNqlSQchSDyR8/zfNVLTfBUniibTUuZ0j06wUpMbVm/fDdmIbicBigQkqqkBuuThXCFC
PJUcvh3a8tv8v+HB32NHRm1X4iLZzTxfYPDlpNIPLMrySX4+ZQd7AHbjIOcHls9sekwW8NrbxwW8
UcMMahUjjUKqgdAAOAKh0/TrPSrNLOwt47e2T7scYwo+lWq82vWVSVoq0Vsv66lpWCiiisBhRRRQ
AUUUUAFFFFABRRRQAUUUUAcR8RbuztNOYXWknUJ5raVLNXO+MShSSWQ/KMJubeR0VhkcZzr74dSW
fh21uPD4SPXbaSK52y4Mc7q4fYd2dgHQEEHAwSRXSeMtNtb/AE2AT2jzPJcQ2wlRgGt1kkVGcZIx
wccAnnkEZqva6nrmgzzp4kZLvT1TcmoWsDfuwD1mUDgn/YBC7eSAc16NKrONKPs3qnqu/wAv0+4h
rXUg1PxC82n6zY6pCNMuJrVobO1nILSsysMhwShySAFByNpJ68W9b1i21CRNJthcSo9xHDdTxxt5
CKW2shk6FjkLtBJywyMZqPxDq2hy3dpYm4gubq4nWOSCA+dKY0zKV8sZyCUCnIxhiTwKwRqVhwsL
PZ6LNGjizs5xLcW7h1dJhCoby14+6ueuSo5ohTUkpcrX9ff0Bs1NQutUT4e6nasWbVdPjEdyFdQX
jGGYq2OjR5AbbnOflyNtcvpzn4j6dcWdnNbWs+jqwtWZjK7pLGQilsAbADtzhjuQE8j5uk8Majqm
uWGlX8mkSm6liMdxqUrCOJ4gzYzEG3OSDxlQoLEg9jxvhu4Xw94tuPsy3b2unpIJY7eLzVWNnXep
2JuwrLIykk5wOBnJ6aUXFTSS51qvya/RX7ifQ6G63a94bsGedNMv4LqS1TSbeLhZhG6eWBuXDKHL
hwQu0gkEYNQaZ4CvodRe1uNQ+zmOaK8Ftp7tHCyNNlky2W+QJxt2nLKSfTYGnyGeTVzbql3rEmIy
ybfJkjJa3J4yFdY13ZwSdowOgv6b/buuXcesF7bTrVo2W3iaPzJvLbYSH+barZTPfGSMcZOTrShF
qLSX69u/dfiFjlNd8L32mrP5dq8o1CeNrkxTTTpMimMGN1ZGK5OTkuAejHHFdr4sguf+ESuNM0yz
a4kuojZovURqyldzZ7Adz3xk4yazNWn8QyB18P6jNfTwsTO22FIUC9UXMZLyHn5dwwepHAPQaDea
jeacW1WyNrdRuUPQLKMAh1GSVBz0JyCCOepyq1J8sZys7Pvr03XyGl0KXhWXU47G4tNVaFjYuIRK
jEg4GfvH7wAKjccHO4EZGTZ8JwQ23hDR47dFSP7HE2F6ElQSfqSSSe+a1lRUztULk5OBjJ9ay5NC
SF3l0q4k06VjuZYgGhc+rRn5ee5XaT61zOane+l7ehVjWoqppl41/p0VxJGI5eUljByEkUlXUHuA
wIz3xVusWmnZjCiiikAUUUUAFFFFABRRRQAUUUUAFFFFAGH4oRms7R/7QgtI47uGUpKP9eUcOEz1
H3SeATkDsCDLJ4hsvLfyYb65IU7RDZSsrn0Dbdvtyceta9FaKceVJrb+uwjy/T/Dk0+tmbU/Dd1d
WQjkZLVXRYIt7I4i8t3UOFYSknBB3DgYAHQHR76DY+gaPDpLqxbynutkDAgjDxR7lySQcgZ4+9XY
UVvPFzk9V+f+YuU42y8Ja5LYraan4jeG1U/La6ZCsQAyTgyNlmHI4AUcYOapN4M1SXWr6SW8naCG
2ijsSlwYFkAZyY3WHYFABUD5Tj73X5a7+ipWLqJt6a+QcqPPL611iPwtH9hvbm4020QERJGi3sLx
NkKzNkPtK4OAp4z8+a1E8KWNxpmpC3jWVbr97ZzSzvIHDKGG4kksN5Y89Q1bcUBg8SztEhWG4txJ
LheGkB2hvrt4PqAvpUum2ktg1xb/AC/ZA++3A6oG5KY9Ac49iB2q5YiVvd06/wBea/ILEumzQXOl
2k9rGIreWFJI0CgbVIBAwOnBq1SKoVQqgAAYAHalrkbuygooopAUtOs5LM3gZh5cty00SA52BgCR
+Lbm/wCBVdoopttu7AKKKKQBRRRQAUUUUAFFFFABRRRQAUUUUAFFFFABRRRQAUUUUAFFFFABRRRQ
AUUUUAFFFFABRRRQAUUUUAFFFFAH/9k=</Data></Thumbnail></Binary></metadata>
